micromagneticmodel/__init__.py
micromagneticmodel/consts.py
micromagneticmodel/driver.py
micromagneticmodel/evolver.py
micromagneticmodel/runner.py
micromagneticmodel/system.py
micromagneticmodel/abstract/__init__.py
micromagneticmodel/abstract/abstract.py
micromagneticmodel/abstract/container.py
micromagneticmodel/abstract/term.py
micromagneticmodel/dynamics/__init__.py
micromagneticmodel/dynamics/damping.py
micromagneticmodel/dynamics/dynamics.py
micromagneticmodel/dynamics/dynamicsterm.py
micromagneticmodel/dynamics/precession.py
micromagneticmodel/dynamics/slonczewski.py
micromagneticmodel/dynamics/zhangli.py
micromagneticmodel/energy/__init__.py
micromagneticmodel/energy/cubicanisotropy.py
micromagneticmodel/energy/demag.py
micromagneticmodel/energy/dmi.py
micromagneticmodel/energy/energy.py
micromagneticmodel/energy/energyterm.py
micromagneticmodel/energy/exchange.py
micromagneticmodel/energy/magnetoelastic.py
micromagneticmodel/energy/rkky.py
micromagneticmodel/energy/uniaxialanisotropy.py
micromagneticmodel/energy/zeeman.py
micromagneticmodel/examples/__init__.py
micromagneticmodel/examples/examples.py
micromagneticmodel/tests/__init__.py
micromagneticmodel/tests/checks.py
micromagneticmodel/tests/test_abstract.py
micromagneticmodel/tests/test_consts.py
micromagneticmodel/tests/test_cubicanisotropy.py
micromagneticmodel/tests/test_damping.py
micromagneticmodel/tests/test_demag.py
micromagneticmodel/tests/test_dmi.py
micromagneticmodel/tests/test_driver.py
micromagneticmodel/tests/test_dynamics.py
micromagneticmodel/tests/test_energy.py
micromagneticmodel/tests/test_examples.py
micromagneticmodel/tests/test_exchange.py
micromagneticmodel/tests/test_init.py
micromagneticmodel/tests/test_magnetoelastic.py
micromagneticmodel/tests/test_precession.py
micromagneticmodel/tests/test_rkky.py
micromagneticmodel/tests/test_runner.py
micromagneticmodel/tests/test_slonczewski.py
micromagneticmodel/tests/test_system.py
micromagneticmodel/tests/test_uniaxialanisotropy.py
micromagneticmodel-0.65.0.dist-info/licenses/LICENSE
micromagneticmodel-0.65.0.dist-info/METADATA
micromagneticmodel-0.65.0.dist-info/WHEEL
micromagneticmodel-0.65.0.dist-info/top_level.txt
micromagneticmodel-0.65.0.dist-info/RECORD
